foutstep/__init__.py
foutstep/stepdft.py
foutstep-0.1.4.dist-info/LICENSE.md
foutstep-0.1.4.dist-info/METADATA
foutstep-0.1.4.dist-info/WHEEL
foutstep-0.1.4.dist-info/top_level.txt
foutstep-0.1.4.dist-info/RECORD
