Metadata-Version: 2.1
Name: foutstep
Version: 0.1.4
Summary: Fourier Transform of Step Functions
Author-email: Jorge Valencia <jorge.valencia@ligo.org>, Rodrigo Tenorio <rodrigo.tenorio@ligo.org>
License: MIT License
Project-URL: Homepage, https://github.com/valencia-jorge/gw-foutstep
Project-URL: Issues, https://github.com/valencia-jorge/gw-foutstep/issues
Classifier: Programming Language :: Python :: 3
Classifier: License :: OSI Approved :: MIT License
Classifier: Topic :: Scientific/Engineering :: Astronomy
Classifier: Topic :: Scientific/Engineering :: Physics
Requires-Python: >=3.11
License-File: LICENSE.md
Requires-Dist: numpy
